qpiai_ml/__init__.py
qpiai_ml/encoding_circuit/__init__.py
qpiai_ml/encoding_circuit/circuit_library/__init__.py
qpiai_ml/encoding_circuit/circuit_library/chebyshev_pqc.py
qpiai_ml/encoding_circuit/circuit_library/chebyshev_rx.py
qpiai_ml/encoding_circuit/circuit_library/chebyshev_tower.py
qpiai_ml/encoding_circuit/circuit_library/highdim_encoding_circuit.py
qpiai_ml/encoding_circuit/circuit_library/hubregtsen_encoding_circuit.py
qpiai_ml/encoding_circuit/circuit_library/multi_control_encoding_circuit.py
qpiai_ml/encoding_circuit/circuit_library/param_z_feature_map.py
qpiai_ml/encoding_circuit/circuit_library/qiskit_encoding_circuit.py
qpiai_ml/encoding_circuit/circuit_library/yz_cx_encoding_circuit.py
qpiai_ml/encoding_circuit/encoding_circuit_base.py
qpiai_ml/encoding_circuit/encoding_circuit_derivatives.py
qpiai_ml/encoding_circuit/layered_encoding_circuit.py
qpiai_ml/encoding_circuit/pruned_encoding_circuit.py
qpiai_ml/encoding_circuit/transpiled_encoding_circuit.py
qpiai_ml/kernel/__init__.py
qpiai_ml/kernel/matrix/__init__.py
qpiai_ml/kernel/matrix/fidelity_kernel.py
qpiai_ml/kernel/matrix/kernel_matrix_base.py
qpiai_ml/kernel/matrix/kernel_util.py
qpiai_ml/kernel/matrix/projected_quantum_kernel.py
qpiai_ml/kernel/matrix/regularization.py
qpiai_ml/kernel/ml/__init__.py
qpiai_ml/kernel/ml/qgpc.py
qpiai_ml/kernel/ml/qgpr.py
qpiai_ml/kernel/ml/qkrr.py
qpiai_ml/kernel/ml/qsvc.py
qpiai_ml/kernel/ml/qsvr.py
qpiai_ml/kernel/optimization/__init__.py
qpiai_ml/kernel/optimization/kernel_loss_base.py
qpiai_ml/kernel/optimization/kernel_optimization_base.py
qpiai_ml/kernel/optimization/kernel_optimizer.py
qpiai_ml/kernel/optimization/negative_log_likelihood.py
qpiai_ml/kernel/optimization/target_alignment.py
qpiai_ml/observables/__init__.py
qpiai_ml/observables/observable_base.py
qpiai_ml/observables/observable_derivatives.py
qpiai_ml/observables/observable_implemented/__init__.py
qpiai_ml/observables/observable_implemented/custom_observable.py
qpiai_ml-0.1.1.dist-info/LICENSE.txt
qpiai_ml-0.1.1.dist-info/METADATA
qpiai_ml-0.1.1.dist-info/WHEEL
qpiai_ml-0.1.1.dist-info/RECORD
