Metadata-Version: 2.1
Name: qpiai-ml
Version: 0.1.1
Summary: 
License: n
Author: Your Name
Author-email: you@example.com
Requires-Python: >=3.9,<4.0
Classifier: License :: Other/Proprietary License
Classifier: Programming Language :: Python :: 3
Classifier: Programming Language :: Python :: 3.9
Classifier: Programming Language :: Python :: 3.10
Classifier: Programming Language :: Python :: 3.11
Classifier: Programming Language :: Python :: 3.12
Requires-Dist: dill (>=0.3,<0.4)
Requires-Dist: numpy (>=1.17,<2.0)
Requires-Dist: qiskit (>=1.0.2,<2.0.0)
Requires-Dist: qiskit-aer (>=0.13.3,<0.14.0)
Requires-Dist: qiskit-algorithms (>=0.3.0,<0.4.0)
Requires-Dist: qiskit-ibm-runtime (>=0.21.2,<0.22.0)
Requires-Dist: qiskit-machine-learning (>=0.7.2,<0.8.0)
Requires-Dist: scipy (>=1.5,<2.0)
Requires-Dist: tqdm (>=4.0,<5.0)
